svy.cp311-win_amd64.pyd
svy.pyi
svy/py.typed
svy-0.3.0.dist-info/METADATA
svy-0.3.0.dist-info/WHEEL
svy-0.3.0.dist-info/entry_points.txt
svy-0.3.0.dist-info/top_level.txt
svy-0.3.0.dist-info/RECORD
